<annotations><filename>38.jpg</filename><size><width>4992</width><height>3328</height><depth>3</depth></size><object><name>1</name><difficult>0</difficult><bndbox><xmin>2760.0</xmin><ymin>391.0</ymin><xmax>2810.0</xmax><ymax>441.0</ymax></bndbox></object><object><name>1</name><difficult>0</difficult><bndbox><xmin>2754.0</xmin><ymin>404.0</ymin><xmax>2804.0</xmax><ymax>454.0</ymax></bndbox></object><object><name>1</name><difficult>0</difficult><bndbox><xmin>2450.0</xmin><ymin>409.0</ymin><xmax>2500.0</xmax><ymax>459.0</ymax></bndbox></object><object><name>1</name><difficult>0</difficult><bndbox><xmin>2708.0</xmin><ymin>425.0</ymin><xmax>2758.0</xmax><ymax>475.0</ymax></bndbox></object><object><name>1</name><difficult>0</difficult><bndbox><xmin>2483.0</xmin><ymin>434.0</ymin><xmax>2533.0</xmax><ymax>484.0</ymax></bndbox></object><object><name>1</name><difficult>0</difficult><bndbox><xmin>2727.0</xmin><ymin>448.0</ymin><xmax>2777.0</xmax><ymax>498.0</ymax></bndbox></object><object><name>1</name><difficult>0</difficult><bndbox><xmin>2490.0</xmin><ymin>459.0</ymin><xmax>2540.0</xmax><ymax>509.0</ymax></bndbox></object><object><name>1</name><difficult>0</difficult><bndbox><xmin>2717.0</xmin><ymin>463.0</ymin><xmax>2767.0</xmax><ymax>513.0</ymax></bndbox></object><object><name>1</name><difficult>0</difficult><bndbox><xmin>2706.0</xmin><ymin>469.0</ymin><xmax>2756.0</xmax><ymax>519.0</ymax></bndbox></object><object><name>1</name><difficult>0</difficult><bndbox><xmin>2741.0</xmin><ymin>470.0</ymin><xmax>2791.0</xmax><ymax>520.0</ymax></bndbox></object><object><name>1</name><difficult>0</difficult><bndbox><xmin>2733.0</xmin><ymin>488.0</ymin><xmax>2783.0</xmax><ymax>538.0</ymax></bndbox></object><object><name>1</name><difficult>0</difficult><bndbox><xmin>2649.0</xmin><ymin>491.0</ymin><xmax>2699.0</xmax><ymax>541.0</ymax></bndbox></object><object><name>1</name><difficult>0</difficult><bndbox><xmin>2538.0</xmin><ymin>493.0</ymin><xmax>2588.0</xmax><ymax>543.0</ymax></bndbox></object><object><name>1</name><difficult>0</difficult><bndbox><xmin>2715.0</xmin><ymin>499.0</ymin><xmax>2765.0</xmax><ymax>549.0</ymax></bndbox></object><object><name>1</name><difficult>0</difficult><bndbox><xmin>2610.0</xmin><ymin>501.0</ymin><xmax>2660.0</xmax><ymax>551.0</ymax></bndbox></object><object><name>1</name><difficult>0</difficult><bndbox><xmin>2693.0</xmin><ymin>501.0</ymin><xmax>2743.0</xmax><ymax>551.0</ymax></bndbox></object><object><name>1</name><difficult>0</difficult><bndbox><xmin>2542.0</xmin><ymin>507.0</ymin><xmax>2592.0</xmax><ymax>557.0</ymax></bndbox></object><object><name>1</name><difficult>0</difficult><bndbox><xmin>2736.0</xmin><ymin>510.0</ymin><xmax>2786.0</xmax><ymax>560.0</ymax></bndbox></object><object><name>1</name><difficult>0</difficult><bndbox><xmin>2647.0</xmin><ymin>516.0</ymin><xmax>2697.0</xmax><ymax>566.0</ymax></bndbox></object><object><name>1</name><difficult>0</difficult><bndbox><xmin>2723.0</xmin><ymin>532.0</ymin><xmax>2773.0</xmax><ymax>582.0</ymax></bndbox></object><object><name>1</name><difficult>0</difficult><bndbox><xmin>2702.0</xmin><ymin>529.0</ymin><xmax>2762.0</xmax><ymax>589.0</ymax></bndbox></object><object><name>1</name><difficult>0</difficult><bndbox><xmin>2688.0</xmin><ymin>544.0</ymin><xmax>2738.0</xmax><ymax>594.0</ymax></bndbox></object><object><name>1</name><difficult>0</difficult><bndbox><xmin>2609.0</xmin><ymin>547.0</ymin><xmax>2659.0</xmax><ymax>597.0</ymax></bndbox></object><object><name>1</name><difficult>0</difficult><bndbox><xmin>2741.0</xmin><ymin>548.0</ymin><xmax>2791.0</xmax><ymax>598.0</ymax></bndbox></object><object><name>1</name><difficult>0</difficult><bndbox><xmin>2627.0</xmin><ymin>556.0</ymin><xmax>2677.0</xmax><ymax>606.0</ymax></bndbox></object><object><name>1</name><difficult>0</difficult><bndbox><xmin>2644.0</xmin><ymin>561.0</ymin><xmax>2694.0</xmax><ymax>611.0</ymax></bndbox></object><object><name>1</name><difficult>0</difficult><bndbox><xmin>2837.0</xmin><ymin>577.0</ymin><xmax>2897.0</xmax><ymax>637.0</ymax></bndbox></object><object><name>1</name><difficult>0</difficult><bndbox><xmin>2523.0</xmin><ymin>1693.0</ymin><xmax>2573.0</xmax><ymax>1743.0</ymax></bndbox></object><object><name>1</name><difficult>0</difficult><bndbox><xmin>2562.0</xmin><ymin>1693.0</ymin><xmax>2612.0</xmax><ymax>1743.0</ymax></bndbox></object><object><name>1</name><difficult>0</difficult><bndbox><xmin>2495.0</xmin><ymin>1716.0</ymin><xmax>2545.0</xmax><ymax>1766.0</ymax></bndbox></object><object><name>1</name><difficult>0</difficult><bndbox><xmin>2550.0</xmin><ymin>1732.0</ymin><xmax>2600.0</xmax><ymax>1782.0</ymax></bndbox></object><object><name>1</name><difficult>0</difficult><bndbox><xmin>2601.0</xmin><ymin>1755.0</ymin><xmax>2661.0</xmax><ymax>1815.0</ymax></bndbox></object><object><name>1</name><difficult>0</difficult><bndbox><xmin>2549.0</xmin><ymin>1767.0</ymin><xmax>2599.0</xmax><ymax>1817.0</ymax></bndbox></object><object><name>1</name><difficult>0</difficult><bndbox><xmin>2564.0</xmin><ymin>1791.0</ymin><xmax>2614.0</xmax><ymax>1841.0</ymax></bndbox></object><object><name>1</name><difficult>0</difficult><bndbox><xmin>2611.0</xmin><ymin>1791.0</ymin><xmax>2661.0</xmax><ymax>1841.0</ymax></bndbox></object><object><name>1</name><difficult>0</difficult><bndbox><xmin>2689.0</xmin><ymin>1848.0</ymin><xmax>2739.0</xmax><ymax>1898.0</ymax></bndbox></object></annotations>