<annotations><filename>471.jpg</filename><size><width>4992</width><height>3328</height><depth>3</depth></size><object><name>1</name><difficult>0</difficult><bndbox><xmin>53.0</xmin><ymin>721.0</ymin><xmax>133.0</xmax><ymax>801.0</ymax></bndbox></object><object><name>1</name><difficult>0</difficult><bndbox><xmin>37.0</xmin><ymin>748.0</ymin><xmax>87.0</xmax><ymax>798.0</ymax></bndbox></object><object><name>1</name><difficult>0</difficult><bndbox><xmin>191.0</xmin><ymin>740.0</ymin><xmax>271.0</xmax><ymax>820.0</ymax></bndbox></object><object><name>1</name><difficult>0</difficult><bndbox><xmin>55.0</xmin><ymin>770.0</ymin><xmax>135.0</xmax><ymax>850.0</ymax></bndbox></object><object><name>1</name><difficult>0</difficult><bndbox><xmin>15.0</xmin><ymin>787.0</ymin><xmax>75.0</xmax><ymax>847.0</ymax></bndbox></object><object><name>1</name><difficult>0</difficult><bndbox><xmin>84.0</xmin><ymin>843.0</ymin><xmax>144.0</xmax><ymax>903.0</ymax></bndbox></object><object><name>1</name><difficult>0</difficult><bndbox><xmin>103.0</xmin><ymin>874.0</ymin><xmax>183.0</xmax><ymax>954.0</ymax></bndbox></object><object><name>1</name><difficult>0</difficult><bndbox><xmin>-21.0</xmin><ymin>919.0</ymin><xmax>29.0</xmax><ymax>969.0</ymax></bndbox></object><object><name>1</name><difficult>0</difficult><bndbox><xmin>253.0</xmin><ymin>942.0</ymin><xmax>303.0</xmax><ymax>992.0</ymax></bndbox></object><object><name>1</name><difficult>0</difficult><bndbox><xmin>-8.0</xmin><ymin>972.0</ymin><xmax>42.0</xmax><ymax>1022.0</ymax></bndbox></object><object><name>1</name><difficult>0</difficult><bndbox><xmin>133.0</xmin><ymin>968.0</ymin><xmax>193.0</xmax><ymax>1028.0</ymax></bndbox></object><object><name>1</name><difficult>0</difficult><bndbox><xmin>186.0</xmin><ymin>979.0</ymin><xmax>236.0</xmax><ymax>1029.0</ymax></bndbox></object><object><name>1</name><difficult>0</difficult><bndbox><xmin>160.0</xmin><ymin>1044.0</ymin><xmax>210.0</xmax><ymax>1094.0</ymax></bndbox></object><object><name>1</name><difficult>0</difficult><bndbox><xmin>251.0</xmin><ymin>1134.0</ymin><xmax>301.0</xmax><ymax>1184.0</ymax></bndbox></object><object><name>1</name><difficult>0</difficult><bndbox><xmin>-19.0</xmin><ymin>1285.0</ymin><xmax>41.0</xmax><ymax>1345.0</ymax></bndbox></object><object><name>1</name><difficult>0</difficult><bndbox><xmin>-25.0</xmin><ymin>1323.0</ymin><xmax>35.0</xmax><ymax>1383.0</ymax></bndbox></object><object><name>1</name><difficult>0</difficult><bndbox><xmin>437.0</xmin><ymin>2456.0</ymin><xmax>497.0</xmax><ymax>2516.0</ymax></bndbox></object></annotations>