<annotations><filename>544.jpg</filename><size><width>4992</width><height>3328</height><depth>3</depth></size><object><name>1</name><difficult>0</difficult><bndbox><xmin>317.0</xmin><ymin>683.0</ymin><xmax>377.0</xmax><ymax>743.0</ymax></bndbox></object><object><name>1</name><difficult>0</difficult><bndbox><xmin>3768.0</xmin><ymin>1381.0</ymin><xmax>3828.0</xmax><ymax>1441.0</ymax></bndbox></object><object><name>1</name><difficult>0</difficult><bndbox><xmin>1126.0</xmin><ymin>1587.0</ymin><xmax>1176.0</xmax><ymax>1637.0</ymax></bndbox></object><object><name>1</name><difficult>0</difficult><bndbox><xmin>100.0</xmin><ymin>1721.0</ymin><xmax>160.0</xmax><ymax>1781.0</ymax></bndbox></object><object><name>1</name><difficult>0</difficult><bndbox><xmin>146.0</xmin><ymin>1770.0</ymin><xmax>196.0</xmax><ymax>1820.0</ymax></bndbox></object><object><name>1</name><difficult>0</difficult><bndbox><xmin>927.0</xmin><ymin>1912.0</ymin><xmax>977.0</xmax><ymax>1962.0</ymax></bndbox></object><object><name>1</name><difficult>0</difficult><bndbox><xmin>1312.0</xmin><ymin>1991.0</ymin><xmax>1372.0</xmax><ymax>2051.0</ymax></bndbox></object><object><name>1</name><difficult>0</difficult><bndbox><xmin>4117.0</xmin><ymin>2044.0</ymin><xmax>4177.0</xmax><ymax>2104.0</ymax></bndbox></object><object><name>1</name><difficult>0</difficult><bndbox><xmin>870.0</xmin><ymin>2119.0</ymin><xmax>920.0</xmax><ymax>2169.0</ymax></bndbox></object><object><name>1</name><difficult>0</difficult><bndbox><xmin>1115.0</xmin><ymin>2152.0</ymin><xmax>1195.0</xmax><ymax>2232.0</ymax></bndbox></object><object><name>1</name><difficult>0</difficult><bndbox><xmin>1297.0</xmin><ymin>2206.0</ymin><xmax>1357.0</xmax><ymax>2266.0</ymax></bndbox></object><object><name>1</name><difficult>0</difficult><bndbox><xmin>921.0</xmin><ymin>2220.0</ymin><xmax>971.0</xmax><ymax>2270.0</ymax></bndbox></object><object><name>1</name><difficult>0</difficult><bndbox><xmin>1407.0</xmin><ymin>2256.0</ymin><xmax>1457.0</xmax><ymax>2306.0</ymax></bndbox></object><object><name>1</name><difficult>0</difficult><bndbox><xmin>2095.0</xmin><ymin>2272.0</ymin><xmax>2155.0</xmax><ymax>2332.0</ymax></bndbox></object><object><name>1</name><difficult>0</difficult><bndbox><xmin>1703.0</xmin><ymin>2429.0</ymin><xmax>1763.0</xmax><ymax>2489.0</ymax></bndbox></object><object><name>1</name><difficult>0</difficult><bndbox><xmin>2951.0</xmin><ymin>2452.0</ymin><xmax>3001.0</xmax><ymax>2502.0</ymax></bndbox></object><object><name>1</name><difficult>0</difficult><bndbox><xmin>364.0</xmin><ymin>2494.0</ymin><xmax>424.0</xmax><ymax>2554.0</ymax></bndbox></object><object><name>1</name><difficult>0</difficult><bndbox><xmin>1924.0</xmin><ymin>2591.0</ymin><xmax>1984.0</xmax><ymax>2651.0</ymax></bndbox></object><object><name>1</name><difficult>0</difficult><bndbox><xmin>1754.0</xmin><ymin>2593.0</ymin><xmax>1834.0</xmax><ymax>2673.0</ymax></bndbox></object><object><name>1</name><difficult>0</difficult><bndbox><xmin>303.0</xmin><ymin>2703.0</ymin><xmax>353.0</xmax><ymax>2753.0</ymax></bndbox></object></annotations>