<annotations><filename>553.jpg</filename><size><width>5616</width><height>3744</height><depth>3</depth></size><object><name>1</name><difficult>0</difficult><bndbox><xmin>2998.0</xmin><ymin>14.0</ymin><xmax>3058.0</xmax><ymax>74.0</ymax></bndbox></object><object><name>1</name><difficult>0</difficult><bndbox><xmin>2802.0</xmin><ymin>221.0</ymin><xmax>2862.0</xmax><ymax>281.0</ymax></bndbox></object><object><name>1</name><difficult>0</difficult><bndbox><xmin>2839.0</xmin><ymin>309.0</ymin><xmax>2889.0</xmax><ymax>359.0</ymax></bndbox></object><object><name>1</name><difficult>0</difficult><bndbox><xmin>2752.0</xmin><ymin>326.0</ymin><xmax>2802.0</xmax><ymax>376.0</ymax></bndbox></object><object><name>1</name><difficult>0</difficult><bndbox><xmin>2684.0</xmin><ymin>612.0</ymin><xmax>2734.0</xmax><ymax>662.0</ymax></bndbox></object><object><name>1</name><difficult>0</difficult><bndbox><xmin>3252.0</xmin><ymin>771.0</ymin><xmax>3312.0</xmax><ymax>831.0</ymax></bndbox></object><object><name>1</name><difficult>0</difficult><bndbox><xmin>3073.0</xmin><ymin>1058.0</ymin><xmax>3133.0</xmax><ymax>1118.0</ymax></bndbox></object><object><name>1</name><difficult>0</difficult><bndbox><xmin>4420.0</xmin><ymin>2899.0</ymin><xmax>4480.0</xmax><ymax>2959.0</ymax></bndbox></object><object><name>1</name><difficult>0</difficult><bndbox><xmin>2160.0</xmin><ymin>2914.0</ymin><xmax>2220.0</xmax><ymax>2974.0</ymax></bndbox></object><object><name>1</name><difficult>0</difficult><bndbox><xmin>4528.0</xmin><ymin>2953.0</ymin><xmax>4608.0</xmax><ymax>3033.0</ymax></bndbox></object><object><name>1</name><difficult>0</difficult><bndbox><xmin>2100.0</xmin><ymin>3031.0</ymin><xmax>2160.0</xmax><ymax>3091.0</ymax></bndbox></object><object><name>1</name><difficult>0</difficult><bndbox><xmin>4179.0</xmin><ymin>3427.0</ymin><xmax>4239.0</xmax><ymax>3487.0</ymax></bndbox></object></annotations>