<annotations><filename>632.jpg</filename><size><width>5616</width><height>3744</height><depth>3</depth></size><object><name>1</name><difficult>0</difficult><bndbox><xmin>1920.0</xmin><ymin>1055.0</ymin><xmax>1980.0</xmax><ymax>1115.0</ymax></bndbox></object><object><name>1</name><difficult>0</difficult><bndbox><xmin>2259.0</xmin><ymin>1461.0</ymin><xmax>2339.0</xmax><ymax>1541.0</ymax></bndbox></object><object><name>1</name><difficult>0</difficult><bndbox><xmin>2437.0</xmin><ymin>1494.0</ymin><xmax>2497.0</xmax><ymax>1554.0</ymax></bndbox></object><object><name>1</name><difficult>0</difficult><bndbox><xmin>2289.0</xmin><ymin>1501.0</ymin><xmax>2369.0</xmax><ymax>1581.0</ymax></bndbox></object><object><name>1</name><difficult>0</difficult><bndbox><xmin>2334.0</xmin><ymin>1511.0</ymin><xmax>2414.0</xmax><ymax>1591.0</ymax></bndbox></object><object><name>1</name><difficult>0</difficult><bndbox><xmin>2359.0</xmin><ymin>1551.0</ymin><xmax>2419.0</xmax><ymax>1611.0</ymax></bndbox></object><object><name>1</name><difficult>0</difficult><bndbox><xmin>2431.0</xmin><ymin>1558.0</ymin><xmax>2491.0</xmax><ymax>1618.0</ymax></bndbox></object><object><name>1</name><difficult>0</difficult><bndbox><xmin>2353.0</xmin><ymin>1565.0</ymin><xmax>2433.0</xmax><ymax>1645.0</ymax></bndbox></object><object><name>1</name><difficult>0</difficult><bndbox><xmin>2459.0</xmin><ymin>1587.0</ymin><xmax>2519.0</xmax><ymax>1647.0</ymax></bndbox></object><object><name>1</name><difficult>0</difficult><bndbox><xmin>2426.0</xmin><ymin>1657.0</ymin><xmax>2476.0</xmax><ymax>1707.0</ymax></bndbox></object><object><name>1</name><difficult>0</difficult><bndbox><xmin>2487.0</xmin><ymin>1682.0</ymin><xmax>2567.0</xmax><ymax>1762.0</ymax></bndbox></object><object><name>1</name><difficult>0</difficult><bndbox><xmin>2500.0</xmin><ymin>1697.0</ymin><xmax>2580.0</xmax><ymax>1777.0</ymax></bndbox></object><object><name>1</name><difficult>0</difficult><bndbox><xmin>2616.0</xmin><ymin>1796.0</ymin><xmax>2676.0</xmax><ymax>1856.0</ymax></bndbox></object><object><name>1</name><difficult>0</difficult><bndbox><xmin>2575.0</xmin><ymin>1991.0</ymin><xmax>2635.0</xmax><ymax>2051.0</ymax></bndbox></object></annotations>