<annotations><filename>711.jpg</filename><size><width>5616</width><height>3744</height><depth>3</depth></size><object><name>1</name><difficult>0</difficult><bndbox><xmin>2122.0</xmin><ymin>1004.0</ymin><xmax>2182.0</xmax><ymax>1064.0</ymax></bndbox></object><object><name>1</name><difficult>0</difficult><bndbox><xmin>2237.0</xmin><ymin>1142.0</ymin><xmax>2297.0</xmax><ymax>1202.0</ymax></bndbox></object><object><name>1</name><difficult>0</difficult><bndbox><xmin>2481.0</xmin><ymin>1263.0</ymin><xmax>2541.0</xmax><ymax>1323.0</ymax></bndbox></object><object><name>1</name><difficult>0</difficult><bndbox><xmin>2434.0</xmin><ymin>1339.0</ymin><xmax>2494.0</xmax><ymax>1399.0</ymax></bndbox></object><object><name>1</name><difficult>0</difficult><bndbox><xmin>2359.0</xmin><ymin>1363.0</ymin><xmax>2419.0</xmax><ymax>1423.0</ymax></bndbox></object><object><name>1</name><difficult>0</difficult><bndbox><xmin>2367.0</xmin><ymin>1486.0</ymin><xmax>2427.0</xmax><ymax>1546.0</ymax></bndbox></object><object><name>1</name><difficult>0</difficult><bndbox><xmin>2581.0</xmin><ymin>1664.0</ymin><xmax>2641.0</xmax><ymax>1724.0</ymax></bndbox></object><object><name>1</name><difficult>0</difficult><bndbox><xmin>2659.0</xmin><ymin>1662.0</ymin><xmax>2739.0</xmax><ymax>1742.0</ymax></bndbox></object><object><name>1</name><difficult>0</difficult><bndbox><xmin>488.0</xmin><ymin>1814.0</ymin><xmax>548.0</xmax><ymax>1874.0</ymax></bndbox></object><object><name>1</name><difficult>0</difficult><bndbox><xmin>2894.0</xmin><ymin>1837.0</ymin><xmax>2944.0</xmax><ymax>1887.0</ymax></bndbox></object><object><name>1</name><difficult>0</difficult><bndbox><xmin>2992.0</xmin><ymin>1842.0</ymin><xmax>3052.0</xmax><ymax>1902.0</ymax></bndbox></object><object><name>1</name><difficult>0</difficult><bndbox><xmin>2943.0</xmin><ymin>1896.0</ymin><xmax>2993.0</xmax><ymax>1946.0</ymax></bndbox></object><object><name>1</name><difficult>0</difficult><bndbox><xmin>727.0</xmin><ymin>1893.0</ymin><xmax>787.0</xmax><ymax>1953.0</ymax></bndbox></object><object><name>1</name><difficult>0</difficult><bndbox><xmin>2871.0</xmin><ymin>1943.0</ymin><xmax>2951.0</xmax><ymax>2023.0</ymax></bndbox></object><object><name>1</name><difficult>0</difficult><bndbox><xmin>3092.0</xmin><ymin>1967.0</ymin><xmax>3142.0</xmax><ymax>2017.0</ymax></bndbox></object><object><name>1</name><difficult>0</difficult><bndbox><xmin>3164.0</xmin><ymin>1968.0</ymin><xmax>3214.0</xmax><ymax>2018.0</ymax></bndbox></object><object><name>1</name><difficult>0</difficult><bndbox><xmin>3071.0</xmin><ymin>1972.0</ymin><xmax>3121.0</xmax><ymax>2022.0</ymax></bndbox></object><object><name>1</name><difficult>0</difficult><bndbox><xmin>2922.0</xmin><ymin>1987.0</ymin><xmax>3002.0</xmax><ymax>2067.0</ymax></bndbox></object><object><name>1</name><difficult>0</difficult><bndbox><xmin>3153.0</xmin><ymin>2016.0</ymin><xmax>3213.0</xmax><ymax>2076.0</ymax></bndbox></object></annotations>