<annotation verified="no">
  <folder>TrainDotted</folder>
  <filename>106</filename>
  <path>/home/vladimir/workspace/data/kaggle_seals/TrainDotted/106.jpg</path>
  <source>
    <database>Unknown</database>
  </source>
  <size>
    <width>5616</width>
    <height>3744</height>
    <depth>3</depth>
  </size>
  <segmented>0</segmented>
  <object>
    <name>p</name>
    <pose>Unspecified</pose>
    <truncated>0</truncated>
    <difficult>0</difficult>
    <bndbox>
      <xmin>3134</xmin>
      <ymin>1445</ymin>
      <xmax>3233</xmax>
      <ymax>1482</ymax>
    </bndbox>
  </object>
  <object>
    <name>p</name>
    <pose>Unspecified</pose>
    <truncated>0</truncated>
    <difficult>0</difficult>
    <bndbox>
      <xmin>2812</xmin>
      <ymin>1316</ymin>
      <xmax>2846</xmax>
      <ymax>1391</ymax>
    </bndbox>
  </object>
  <object>
    <name>p</name>
    <pose>Unspecified</pose>
    <truncated>0</truncated>
    <difficult>0</difficult>
    <bndbox>
      <xmin>2774</xmin>
      <ymin>1439</ymin>
      <xmax>2841</xmax>
      <ymax>1483</ymax>
    </bndbox>
  </object>
  <object>
    <name>p</name>
    <pose>Unspecified</pose>
    <truncated>0</truncated>
    <difficult>0</difficult>
    <bndbox>
      <xmin>3015</xmin>
      <ymin>1330</ymin>
      <xmax>3083</xmax>
      <ymax>1386</ymax>
    </bndbox>
  </object>
  <object>
    <name>b</name>
    <pose>Unspecified</pose>
    <truncated>0</truncated>
    <difficult>0</difficult>
    <bndbox>
      <xmin>3018</xmin>
      <ymin>1293</ymin>
      <xmax>3084</xmax>
      <ymax>1328</ymax>
    </bndbox>
  </object>
  <object>
    <name>b</name>
    <pose>Unspecified</pose>
    <truncated>0</truncated>
    <difficult>0</difficult>
    <bndbox>
      <xmin>3106</xmin>
      <ymin>1285</ymin>
      <xmax>3153</xmax>
      <ymax>1343</ymax>
    </bndbox>
  </object>
  <object>
    <name>b</name>
    <pose>Unspecified</pose>
    <truncated>0</truncated>
    <difficult>0</difficult>
    <bndbox>
      <xmin>3107</xmin>
      <ymin>1367</ymin>
      <xmax>3158</xmax>
      <ymax>1410</ymax>
    </bndbox>
  </object>
  <object>
    <name>b</name>
    <pose>Unspecified</pose>
    <truncated>0</truncated>
    <difficult>0</difficult>
    <bndbox>
      <xmin>2877</xmin>
      <ymin>1332</ymin>
      <xmax>2936</xmax>
      <ymax>1367</ymax>
    </bndbox>
  </object>
  <object>
    <name>b</name>
    <pose>Unspecified</pose>
    <truncated>0</truncated>
    <difficult>0</difficult>
    <bndbox>
      <xmin>2847</xmin>
      <ymin>1395</ymin>
      <xmax>2877</xmax>
      <ymax>1436</ymax>
    </bndbox>
  </object>
</annotation>
